[
	{
		"inputs": [],
		"stateMutability": "nonpayable",
		"type": "constructor"
	},
	{
		"anonymous": false,
		"inputs": [
			{
				"indexed": false,
				"internalType": "uint256",
				"name": "luckyPackageId",
				"type": "uint256"
			},
			{
				"indexed": false,
				"internalType": "uint256",
				"name": "createTime",
				"type": "uint256"
			},
			{
				"indexed": false,
				"internalType": "uint256",
				"name": "openTime",
				"type": "uint256"
			},
			{
				"indexed": false,
				"internalType": "uint256",
				"name": "exprTime",
				"type": "uint256"
			},
			{
				"indexed": false,
				"internalType": "address",
				"name": "coinTokenAddr",
				"type": "address"
			},
			{
				"indexed": false,
				"internalType": "uint256",
				"name": "amount",
				"type": "uint256"
			},
			{
				"indexed": false,
				"internalType": "uint256",
				"name": "count",
				"type": "uint256"
			}
		],
		"name": "event_create",
		"type": "event"
	},
	{
		"anonymous": false,
		"inputs": [
			{
				"indexed": false,
				"internalType": "uint256",
				"name": "luckyPackageId",
				"type": "uint256"
			},
			{
				"indexed": false,
				"internalType": "address",
				"name": "openAddr",
				"type": "address"
			},
			{
				"indexed": false,
				"internalType": "uint256",
				"name": "openAmount",
				"type": "uint256"
			},
			{
				"indexed": false,
				"internalType": "uint256",
				"name": "remainToal",
				"type": "uint256"
			}
		],
		"name": "event_open",
		"type": "event"
	},
	{
		"inputs": [],
		"name": "counter",
		"outputs": [
			{
				"internalType": "uint256",
				"name": "",
				"type": "uint256"
			}
		],
		"stateMutability": "view",
		"type": "function"
	},
	{
		"inputs": [
			{
				"internalType": "address",
				"name": "_coinTokenAddr",
				"type": "address"
			},
			{
				"internalType": "uint256",
				"name": "_amount",
				"type": "uint256"
			},
			{
				"internalType": "uint256",
				"name": "_count",
				"type": "uint256"
			},
			{
				"internalType": "uint256",
				"name": "_opentime",
				"type": "uint256"
			},
			{
				"internalType": "uint256",
				"name": "_daysAfterEnd",
				"type": "uint256"
			},
			{
				"internalType": "string",
				"name": "_openhashStr",
				"type": "string"
			}
		],
		"name": "create",
		"outputs": [],
		"stateMutability": "payable",
		"type": "function"
	},
	{
		"inputs": [
			{
				"internalType": "uint256",
				"name": "luckyPackageId",
				"type": "uint256"
			}
		],
		"name": "info",
		"outputs": [
			{
				"internalType": "address",
				"name": "",
				"type": "address"
			},
			{
				"internalType": "uint256",
				"name": "",
				"type": "uint256"
			},
			{
				"internalType": "uint256",
				"name": "",
				"type": "uint256"
			},
			{
				"internalType": "address",
				"name": "",
				"type": "address"
			},
			{
				"internalType": "uint256",
				"name": "",
				"type": "uint256"
			},
			{
				"internalType": "uint256",
				"name": "",
				"type": "uint256"
			},
			{
				"internalType": "string",
				"name": "",
				"type": "string"
			}
		],
		"stateMutability": "view",
		"type": "function"
	},
	{
		"inputs": [
			{
				"internalType": "uint256",
				"name": "luckyPackageId",
				"type": "uint256"
			},
			{
				"internalType": "string",
				"name": "_openHashstr",
				"type": "string"
			}
		],
		"name": "open",
		"outputs": [],
		"stateMutability": "nonpayable",
		"type": "function"
	},
	{
		"inputs": [],
		"name": "owner",
		"outputs": [
			{
				"internalType": "address",
				"name": "",
				"type": "address"
			}
		],
		"stateMutability": "view",
		"type": "function"
	},
	{
		"inputs": [
			{
				"internalType": "uint256",
				"name": "",
				"type": "uint256"
			}
		],
		"name": "packageInfos",
		"outputs": [
			{
				"internalType": "address",
				"name": "creator",
				"type": "address"
			},
			{
				"internalType": "uint256",
				"name": "packageTotal",
				"type": "uint256"
			},
			{
				"internalType": "uint256",
				"name": "moneyTotal",
				"type": "uint256"
			},
			{
				"internalType": "address",
				"name": "luckyTokenAddr",
				"type": "address"
			},
			{
				"internalType": "uint256",
				"name": "createTime",
				"type": "uint256"
			},
			{
				"internalType": "uint256",
				"name": "openTime",
				"type": "uint256"
			},
			{
				"internalType": "uint256",
				"name": "endtime",
				"type": "uint256"
			},
			{
				"internalType": "string",
				"name": "openHashstr",
				"type": "string"
			}
		],
		"stateMutability": "view",
		"type": "function"
	},
	{
		"inputs": [
			{
				"internalType": "uint256",
				"name": "luckyPackageId",
				"type": "uint256"
			},
			{
				"internalType": "address",
				"name": "openerAddr",
				"type": "address"
			}
		],
		"name": "record",
		"outputs": [
			{
				"internalType": "uint256",
				"name": "",
				"type": "uint256"
			}
		],
		"stateMutability": "view",
		"type": "function"
	},
	{
		"inputs": [
			{
				"internalType": "uint256",
				"name": "luckyPackageId",
				"type": "uint256"
			}
		],
		"name": "recordAll",
		"outputs": [
			{
				"components": [
					{
						"internalType": "address",
						"name": "openedAddr",
						"type": "address"
					},
					{
						"internalType": "uint256",
						"name": "openAmount",
						"type": "uint256"
					}
				],
				"internalType": "struct LuckyPackage.OPENINFO[]",
				"name": "",
				"type": "tuple[]"
			}
		],
		"stateMutability": "view",
		"type": "function"
	},
	{
		"inputs": [
			{
				"internalType": "uint256",
				"name": "luckyPackageId",
				"type": "uint256"
			}
		],
		"name": "withdraw",
		"outputs": [],
		"stateMutability": "nonpayable",
		"type": "function"
	},
	{
		"inputs": [
			{
				"internalType": "uint256",
				"name": "luckyPackageId",
				"type": "uint256"
			}
		],
		"name": "withdrawforadmin",
		"outputs": [],
		"stateMutability": "payable",
		"type": "function"
	},
	{
		"stateMutability": "payable",
		"type": "receive"
	}
]